{
  "schema_version": "1.0.0",
  "namespaces": [
    {
      "name": "Vaadin",
      "description": "",
      "summary": "",
      "sourceRange": {
        "file": "src/vaadin-list-box.html",
        "start": {
          "line": 101,
          "column": 6
        },
        "end": {
          "line": 101,
          "column": 52
        }
      },
      "elements": [
        {
          "description": "`<vaadin-list-box>` is a Polymer 2 element for menus\n\n```\n  <vaadin-list-box selected=\"2\">\n    <vaadin-item>Item 1</vaadin-item>\n    <vaadin-item>Item 2</vaadin-item>\n    <vaadin-item>Item 3</vaadin-item>\n    <vaadin-item>Item 4</vaadin-item>\n  </vaadin-list-box>\n```\n\n### Styling\n\nThe following shadow DOM parts are available for styling:\n\nPart name         | Description\n------------------|------------------------\n`items`           | The items container\n\nSee [ThemableMixin – how to apply styles for shadow parts](https://github.com/vaadin/vaadin-themable-mixin/wiki)",
          "summary": "",
          "path": "src/vaadin-list-box.html",
          "properties": [
            {
              "name": "orientation",
              "type": "?",
              "description": "",
              "privacy": "private",
              "sourceRange": {
                "start": {
                  "line": 80,
                  "column": 12
                },
                "end": {
                  "line": 82,
                  "column": 13
                }
              },
              "metadata": {
                "polymer": {
                  "readOnly": true
                }
              }
            }
          ],
          "methods": [
            {
              "name": "ready",
              "description": "",
              "privacy": "protected",
              "sourceRange": {
                "start": {
                  "line": 86,
                  "column": 8
                },
                "end": {
                  "line": 89,
                  "column": 9
                }
              },
              "metadata": {},
              "params": []
            }
          ],
          "staticMethods": [],
          "demos": [
            {
              "url": "demo/index.html",
              "description": ""
            }
          ],
          "metadata": {},
          "sourceRange": {
            "start": {
              "line": 66,
              "column": 6
            },
            "end": {
              "line": 94,
              "column": 7
            }
          },
          "privacy": "public",
          "superclass": "HTMLElement",
          "name": "Vaadin.ListBoxElement",
          "attributes": [],
          "events": [],
          "styling": {
            "cssVariables": [],
            "selectors": []
          },
          "slots": [
            {
              "description": "",
              "name": "",
              "range": {
                "file": "src/vaadin-list-box.html",
                "start": {
                  "line": 33,
                  "column": 6
                },
                "end": {
                  "line": 33,
                  "column": 19
                }
              }
            }
          ],
          "tagname": "vaadin-list-box",
          "mixins": [
            "Vaadin.ListMixin",
            "Vaadin.ThemableMixin"
          ]
        }
      ]
    }
  ]
}
